{
  "Name": "Planet",
  "Aliases": ["World"],
  "Tags": ["oracles", "template", "location"],
  "Children": [
    "Desert World",
    "Furnace World",
    "Grave World",
    "Ice World",
    "Jovian World",
    "Jungle World",
    "Ocean World",
    "Rocky World",
    "Shattered World",
    "Tainted World",
    "Vital World"
  ],
  "Source": { "Name": "Starforged Backer Preview", "Version": "042721" },
  "Inherits": [{ "From": "Space", "Oracles": ["Stellar Object"] }],
  "Oracles": [
    {
      "Name": "Planetary Class",
      "Initial": true,
      "Table": [
        { "Chance": 15, "Description": "▶️Desert World" },
        { "Chance": 30, "Description": "▶️Furnace World" },
        { "Chance": 35, "Description": "▶️Grave World" },
        { "Chance": 50, "Description": "▶️Ice World" },
        { "Chance": 65, "Description": "▶️Jovian World" },
        { "Chance": 70, "Description": "▶️Jungle World" },
        { "Chance": 75, "Description": "▶️Ocean World" },
        { "Chance": 90, "Description": "▶️Rocky World" },
        { "Chance": 92, "Description": "▶️Shattered World" },
        { "Chance": 98, "Description": "▶️Tainted World" },
        { "Chance": 100, "Description": "▶️Vital World" }
      ]
    },
    {
      "Name": "Peril",
      "Tables": [
        {
          "Aliases": ["Lifebearing Planetside Peril"],
          "Tags": ["repeatable", "peril"],
          "Requires": {
            "Location": "Planetside",
            "Life": [
              "Simple",
              "Sparse",
              "Diverse",
              "Bountiful",
              "Overrun",
              "Lifebearing"
            ]
          },
          "Table": [
            { "Chance": 3, "Description": "Corrupted or mutated lifeform" },
            {
              "Chance": 6,
              "Description": "Signs of a lifeform's power or cunning"
            },
            {
              "Chance": 9,
              "Description": "Hazardous plant life or malignant spores"
            },
            { "Chance": 12, "Description": "Lifeform hunts for prey" },
            { "Chance": 15, "Description": "Lifeform lairs here" },
            {
              "Chance": 18,
              "Description": "Lifeforms guided by a greater threat"
            },
            { "Chance": 21, "Description": "Lifeforms spooked or stampeding" },
            { "Chance": 24, "Description": "Threatening lifeform draws near" },
            {
              "Chance": 27,
              "Description": "Life is revealed or takes an unexpected form"
            },
            { "Chance": 30, "Description": "Blocked or impassible path" },
            {
              "Chance": 33,
              "Description": "Corrosive substance or environment"
            },
            {
              "Chance": 36,
              "Description": "Disturbing remains or evidence of death"
            },
            { "Chance": 39, "Description": "Drastic environmental change" },
            { "Chance": 42, "Description": "Enemy holds this area" },
            { "Chance": 45, "Description": "Entangling or engulfing hazard" },
            { "Chance": 48, "Description": "Equipment fails or malfunctions" },
            { "Chance": 51, "Description": "Guarded or patrolled path" },
            { "Chance": 54, "Description": "Led astray" },
            { "Chance": 57, "Description": "Lost the path" },
            { "Chance": 60, "Description": "Meteorites fall from the sky" },
            { "Chance": 63, "Description": "Radiated area or object" },
            {
              "Chance": 66,
              "Description": "Realization that something was left behind"
            },
            { "Chance": 69, "Description": "Seismic or volcanic upheaval" },
            {
              "Chance": 72,
              "Description": "Signs of a lurking or trailing foe"
            },
            { "Chance": 75, "Description": "Storm or atmospheric disruption" },
            { "Chance": 78, "Description": "Toxic or sickening environment" },
            { "Chance": 81, "Description": "Trap or alarm" },
            { "Chance": 84, "Description": "Treacherous or arduous path" },
            { "Chance": 87, "Description": "Troubling visions or apparitions" },
            {
              "Chance": 90,
              "Description": "Visibility hindered by atmospheric effects"
            },
            {
              "Chance": 93,
              "Description": "Worrying arrival of a ship or vehicle"
            },
            {
              "Chance": 96,
              "Description": "Wreckage or ruins portend a new threat"
            },
            { "Chance": 99, "Description": "▶️Action + Theme" },
            { "Chance": 100, "Description": "[Roll twice]" }
          ]
        },
        {
          "Aliases": ["Lifeless Planetside Peril"],
          "Tags": ["repeatable", "fragment"],
          "Requires": {
            "Location": "Planetside",
            "Life": ["None", "Extinct", "Lifeless"]
          },
          "Table": [
            {
              "Chance": 3,
              "Description": "Life is revealed or takes an unexpected form"
            },
            { "Chance": 7, "Description": "Blocked or impassible path" },
            {
              "Chance": 11,
              "Description": "Corrosive substance or environment"
            },
            {
              "Chance": 15,
              "Description": "Disturbing remains or evidence of death"
            },
            { "Chance": 19, "Description": "Drastic environmental change" },
            { "Chance": 23, "Description": "Enemy holds this area" },
            { "Chance": 27, "Description": "Entangling or engulfing hazard" },
            { "Chance": 31, "Description": "Equipment fails or malfunctions" },
            { "Chance": 35, "Description": "Guarded or patrolled path" },
            { "Chance": 39, "Description": "Led astray" },
            { "Chance": 43, "Description": "Lost the path" },
            { "Chance": 47, "Description": "Meteorites fall from the sky" },
            { "Chance": 51, "Description": "Radiated area or object" },
            {
              "Chance": 55,
              "Description": "Realization that something was left behind"
            },
            { "Chance": 59, "Description": "Seismic or volcanic upheaval" },
            {
              "Chance": 63,
              "Description": "Signs of a lurking or trailing foe"
            },
            { "Chance": 67, "Description": "Storm or atmospheric disruption" },
            { "Chance": 71, "Description": "Toxic or sickening environment" },
            { "Chance": 75, "Description": "Trap or alarm" },
            { "Chance": 79, "Description": "Treacherous or arduous path" },
            { "Chance": 83, "Description": "Troubling visions or apparitions" },
            {
              "Chance": 87,
              "Description": "Visibility hindered by atmospheric effects"
            },
            {
              "Chance": 91,
              "Description": "Worrying arrival of a ship or vehicle"
            },
            {
              "Chance": 95,
              "Description": "Wreckage or ruins portend a new threat"
            },
            { "Chance": 99, "Description": "▶️Action + Theme" },
            { "Chance": 100, "Description": "[Roll twice]" }
          ]
        }
      ]
    },
    {
      "Name": "Opportunity",
      "Tables": [
        {
          "Aliases": ["Lifebearing Planetside Opportunity"],
          "Tags": ["repeatable", "opportunity"],
          "Requires": {
            "Location": "Planetside",
            "Life": [
              "Simple",
              "Sparse",
              "Diverse",
              "Bountiful",
              "Overrun",
              "Lifebearing"
            ]
          },
          "Table": [
            {
              "Chance": 4,
              "Description": "Clue to a lifeform's nature or vulnerabilities"
            },
            {
              "Chance": 8,
              "Description": "Friendly interaction with a benign lifeform"
            },
            {
              "Chance": 12,
              "Description": "Hunting or foraging opportunities are plentiful"
            },
            {
              "Chance": 16,
              "Description": "Interesting or helpful aspect of benign creatures"
            },
            {
              "Chance": 20,
              "Description": "Interesting or helpful aspect of local plant life"
            },
            {
              "Chance": 24,
              "Description": "Encounter reveals unexpected benign lifeforms"
            },
            { "Chance": 28, "Description": "Abandoned camp or vehicle" },
            {
              "Chance": 32,
              "Description": "Advance warning of an environmental threat"
            },
            {
              "Chance": 36,
              "Description": "Clear path through otherwise perilous terrain"
            },
            {
              "Chance": 40,
              "Description": "Clue offers insight into a current quest or mystery"
            },
            {
              "Chance": 44,
              "Description": "Clue to the history or nature of this place"
            },
            {
              "Chance": 48,
              "Description": "Evidence that others have passed this way"
            },
            {
              "Chance": 52,
              "Description": "Foe reveals themselves or tips their hand"
            },
            {
              "Chance": 56,
              "Description": "Fortuitous change in the weather or atmosphere"
            },
            {
              "Chance": 60,
              "Description": "Friendly traveler crosses your path"
            },
            {
              "Chance": 64,
              "Description": "Helpful resource is in ample supply"
            },
            {
              "Chance": 68,
              "Description": "Impressive vista offers comfort or inspiration"
            },
            { "Chance": 72, "Description": "Interesting artifact or device" },
            {
              "Chance": 76,
              "Description": "Interesting site offers opportunities for exploration"
            },
            {
              "Chance": 80,
              "Description": "Moment of fellowship or inner peace"
            },
            {
              "Chance": 84,
              "Description": "Opening to distract, escape, or avoid foes"
            },
            { "Chance": 88, "Description": "Opening to get the drop on a foe" },
            {
              "Chance": 92,
              "Description": "Plea for help from a potential benefactor"
            },
            {
              "Chance": 96,
              "Description": "Refuge offers a place to hide, plan, or recover"
            },
            {
              "Chance": 100,
              "Description": "Vantage point reveals the lay of the land"
            }
          ]
        },
        {
          "Aliases": ["Lifeless Planetside Opportunity"],
          "Tags": ["repeatable", "fragment"],
          "Requires": {
            "Location": "Planetside",
            "Life": ["None", "Extinct", "Lifeless"]
          },
          "Table": [
            {
              "Chance": 5,
              "Description": "Encounter reveals unexpected benign lifeforms"
            },
            { "Chance": 10, "Description": "Abandoned camp or vehicle" },
            {
              "Chance": 15,
              "Description": "Advance warning of an environmental threat"
            },
            {
              "Chance": 20,
              "Description": "Clear path through otherwise perilous terrain"
            },
            {
              "Chance": 25,
              "Description": "Clue offers insight into a current quest or mystery"
            },
            {
              "Chance": 30,
              "Description": "Clue to the history or nature of this place"
            },
            {
              "Chance": 35,
              "Description": "Evidence that others have passed this way"
            },
            {
              "Chance": 40,
              "Description": "Foe reveals themselves or tips their hand"
            },
            {
              "Chance": 45,
              "Description": "Fortuitous change in the weather or atmosphere"
            },
            {
              "Chance": 50,
              "Description": "Friendly traveler crosses your path"
            },
            {
              "Chance": 55,
              "Description": "Helpful resource is in ample supply"
            },
            {
              "Chance": 60,
              "Description": "Impressive vista offers comfort or inspiration"
            },
            { "Chance": 65, "Description": "Interesting artifact or device" },
            {
              "Chance": 70,
              "Description": "Interesting site offers opportunities for exploration"
            },
            {
              "Chance": 75,
              "Description": "Moment of fellowship or inner peace"
            },
            {
              "Chance": 80,
              "Description": "Opening to distract, escape, or avoid foes"
            },
            { "Chance": 85, "Description": "Opening to get the drop on a foe" },
            {
              "Chance": 90,
              "Description": "Plea for help from a potential benefactor"
            },
            {
              "Chance": 95,
              "Description": "Refuge offers a place to hide, plan, or recover"
            },
            {
              "Chance": 100,
              "Description": "Vantage point reveals the lay of the land"
            }
          ]
        }
      ]
    }
  ]
}
